fyers_token_manager/__init__.py
fyers_token_manager/main.py
fyers_token_manager-0.0.2.dist-info/LICENSE
fyers_token_manager-0.0.2.dist-info/METADATA
fyers_token_manager-0.0.2.dist-info/WHEEL
fyers_token_manager-0.0.2.dist-info/top_level.txt
fyers_token_manager-0.0.2.dist-info/RECORD
