Metadata-Version: 2.1
Name: fyers-token-manager
Version: 0.0.2
Summary: Fyers Token Manager
Home-page: https://github.com/krunaldodiya/fyers-token-manager
Author: Krunal Dodiya
Author-email: kunal.dodiya1@gmail.com
License: UNKNOWN
Platform: UNKNOWN
Classifier: Programming Language :: Python :: 3
Classifier: Operating System :: OS Independent
License-File: LICENSE
Requires-Dist: requests
